splinetorch/__init__.py
splinetorch/b_spline.py
splinetorch/b_spline_basis.py
splinetorch-0.0.2.dist-info/METADATA
splinetorch-0.0.2.dist-info/WHEEL
splinetorch-0.0.2.dist-info/top_level.txt
splinetorch-0.0.2.dist-info/RECORD
