Metadata-Version: 2.1
Name: splinetorch
Version: 0.0.2
Summary: SplineTorch is a Python package for fitting splines in PyTorch.
Home-page: https://github.com/joakimwallmark/splinetorch
Author: Joakim Wallmark
Author-email: wallmark.joakim@gmail.com
License: MIT
Requires-Python: >=3.10
Requires-Dist: torch <4.0.0,>=2.1.1
Requires-Dist: numpy <3.0.0,>=1.24.1
Requires-Dist: pandas <4.0.0,>=2.2.0
Requires-Dist: matplotlib <5.0.0,>=3.8.0
